.gitignore
MANIFEST.in
README.rst
bootstrap.py
buildout.cfg
setup.py
collective/__init__.py
collective.js.nomensamediaplayer.egg-info/PKG-INFO
collective.js.nomensamediaplayer.egg-info/SOURCES.txt
collective.js.nomensamediaplayer.egg-info/dependency_links.txt
collective.js.nomensamediaplayer.egg-info/entry_points.txt
collective.js.nomensamediaplayer.egg-info/namespace_packages.txt
collective.js.nomensamediaplayer.egg-info/not-zip-safe
collective.js.nomensamediaplayer.egg-info/requires.txt
collective.js.nomensamediaplayer.egg-info/top_level.txt
collective/js/__init__.py
collective/js/nomensamediaplayer/__init__.py
collective/js/nomensamediaplayer/configure.zcml
collective/js/nomensamediaplayer/upgrades.py
collective/js/nomensamediaplayer/upgrades.zcml
collective/js/nomensamediaplayer/profiles/default/cssregistry.xml
collective/js/nomensamediaplayer/profiles/default/jsregistry.xml
collective/js/nomensamediaplayer/profiles/default/metadata.xml
collective/js/nomensamediaplayer/resources/core/css/player-core.css
collective/js/nomensamediaplayer/resources/core/css/player-core.min.css
collective/js/nomensamediaplayer/resources/core/javascript/jquery.player.js
collective/js/nomensamediaplayer/resources/core/javascript/jquery.player.min.js
collective/js/nomensamediaplayer/resources/custom/css/player-theme.css
collective/js/nomensamediaplayer/resources/custom/css/player-theme.min.css
collective/js/nomensamediaplayer/resources/custom/images/bg.gif
collective/js/nomensamediaplayer/resources/custom/images/button-cc-off.gif
collective/js/nomensamediaplayer/resources/custom/images/button-cc.gif
collective/js/nomensamediaplayer/resources/custom/images/button-forward.gif
collective/js/nomensamediaplayer/resources/custom/images/button-pause.gif
collective/js/nomensamediaplayer/resources/custom/images/button-play.gif
collective/js/nomensamediaplayer/resources/custom/images/button-restart.gif
collective/js/nomensamediaplayer/resources/custom/images/button-rewind.gif
collective/js/nomensamediaplayer/resources/custom/images/button-voldown.gif
collective/js/nomensamediaplayer/resources/custom/images/button-volmute.gif
collective/js/nomensamediaplayer/resources/custom/images/button-volon.gif
collective/js/nomensamediaplayer/resources/custom/images/button-volup.gif
collective/js/nomensamediaplayer/resources/custom/images/logo.gif
collective/js/nomensamediaplayer/resources/custom/images/nomensa-logo-small.gif
