Metadata-Version: 1.0
Name: collective.js.nomensamediaplayer
Version: 1.0
Summary: Nomensa's Accessible Media Player registration in Plone resources registries
Home-page: https://github.com/collective/collective.js.nomensamediaplayer
Author: JeanMichel FRANCOIS aka toutpt
Author-email: toutpt@gmail.com
License: GPL
Keywords: plone nomensa media player
Platform: UNKNOWN
Classifier: Programming Language :: Python
